pylibseekdb/libseekdb_python.cpython-314-darwin.so
pylibseekdb/seekdb_test.py
pylibseekdb/__init__.py
pylibseekdb/cli.py
pylibseekdb/.dylibs/libabsl_cord.2601.0.0.dylib
pylibseekdb/.dylibs/libabsl_log_globals.2601.0.0.dylib
pylibseekdb/.dylibs/libabsl_log_internal_proto.2601.0.0.dylib
pylibseekdb/.dylibs/libabsl_cord_internal.2601.0.0.dylib
pylibseekdb/.dylibs/libabsl_log_internal_check_op.2601.0.0.dylib
pylibseekdb/.dylibs/libabsl_base.2601.0.0.dylib
pylibseekdb/.dylibs/libabsl_vlog_config_internal.2601.0.0.dylib
pylibseekdb/.dylibs/libabsl_demangle_internal.2601.0.0.dylib
pylibseekdb/.dylibs/libabsl_flags_reflection.2601.0.0.dylib
pylibseekdb/.dylibs/libbrotlicommon.1.2.0.dylib
pylibseekdb/.dylibs/libabsl_int128.2601.0.0.dylib
pylibseekdb/.dylibs/libabsl_crc_cord_state.2601.0.0.dylib
pylibseekdb/.dylibs/libabsl_city.2601.0.0.dylib
pylibseekdb/.dylibs/libbrotlidec.1.2.0.dylib
pylibseekdb/.dylibs/libabsl_log_internal_log_sink_set.2601.0.0.dylib
pylibseekdb/.dylibs/libabsl_log_entry.2601.0.0.dylib
pylibseekdb/.dylibs/libutf8proc.3.2.3.dylib
pylibseekdb/.dylibs/libabsl_crc_internal.2601.0.0.dylib
pylibseekdb/.dylibs/libthrift-0.22.0.dylib
pylibseekdb/.dylibs/libabsl_cordz_functions.2601.0.0.dylib
pylibseekdb/.dylibs/libabsl_symbolize.2601.0.0.dylib
pylibseekdb/.dylibs/libabsl_malloc_internal.2601.0.0.dylib
pylibseekdb/.dylibs/libabsl_flags_marshalling.2601.0.0.dylib
pylibseekdb/.dylibs/libabsl_str_format_internal.2601.0.0.dylib
pylibseekdb/.dylibs/libabsl_strings_internal.2601.0.0.dylib
pylibseekdb/.dylibs/libabsl_log_internal_message.2601.0.0.dylib
pylibseekdb/.dylibs/libabsl_log_internal_nullguard.2601.0.0.dylib
pylibseekdb/.dylibs/libabsl_strings.2601.0.0.dylib
pylibseekdb/.dylibs/libabsl_examine_stack.2601.0.0.dylib
pylibseekdb/.dylibs/libabsl_raw_hash_set.2601.0.0.dylib
pylibseekdb/.dylibs/libabsl_synchronization.2601.0.0.dylib
pylibseekdb/.dylibs/libabsl_utf8_for_code_point.2601.0.0.dylib
pylibseekdb-1.1.0.dist-info/RECORD
pylibseekdb-1.1.0.dist-info/WHEEL
pylibseekdb-1.1.0.dist-info/top_level.txt
pylibseekdb-1.1.0.dist-info/METADATA
